objectstore/__init__.py
objectstore/archive_pgtables.py
objectstore/databasedumps.py
objectstore/db_objectstore.py
objectstore/objectstore.py
objectstore/upload_db.py
datapunt_objectstore-2020.9.7.dist-info/LICENSE.rst
datapunt_objectstore-2020.9.7.dist-info/METADATA
datapunt_objectstore-2020.9.7.dist-info/WHEEL
datapunt_objectstore-2020.9.7.dist-info/top_level.txt
datapunt_objectstore-2020.9.7.dist-info/RECORD
