Metadata-Version: 2.1
Name: datapunt-objectstore
Version: 2020.9.7
Summary: Datapunt Amsterdam objectstore module
Home-page: https://github.com/amsterdam/objectstore
Author: Datapunt Amsterdam
Author-email: datapunt@amsterdam.nl
License: Mozilla Public License Version 2.0
Platform: UNKNOWN
Classifier: Development Status :: 3 - Alpha
Classifier: Intended Audience :: Developers
Classifier: Natural Language :: English
Classifier: Programming Language :: Python
Classifier: Programming Language :: Python :: 3.6
Classifier: License :: OSI Approved :: Mozilla Public License 2.0 (MPL 2.0)
Requires-Dist: python-dateutil
Requires-Dist: python-swiftclient
Requires-Dist: datapunt-config-loader
Requires-Dist: python-keystoneclient
Provides-Extra: dev
Requires-Dist: pytest ; extra == 'dev'
Requires-Dist: pytest-cov ; extra == 'dev'
Requires-Dist: pylint ; extra == 'dev'
Requires-Dist: twine ; extra == 'dev'
Provides-Extra: docs
Requires-Dist: sphinx ; extra == 'docs'
Requires-Dist: sphinx-autobuild ; extra == 'docs'
Requires-Dist: sphinx-rtd-theme ; extra == 'docs'
